splinkclickhouse/__init__.py
splinkclickhouse/column_expression.py
splinkclickhouse/comparison_level_library.py
splinkclickhouse/comparison_library.py
splinkclickhouse/custom_sql.py
splinkclickhouse/database_api.py
splinkclickhouse/dataframe.py
splinkclickhouse/dialect.py
splinkclickhouse/chdb/__init__.py
splinkclickhouse/chdb/database_api.py
splinkclickhouse/chdb/dataframe.py
splinkclickhouse/clickhouse_server/__init__.py
splinkclickhouse/clickhouse_server/database_api.py
splinkclickhouse/clickhouse_server/dataframe.py
splinkclickhouse-0.4.1.dist-info/METADATA
splinkclickhouse-0.4.1.dist-info/WHEEL
splinkclickhouse-0.4.1.dist-info/licenses/LICENSE
splinkclickhouse-0.4.1.dist-info/RECORD
