Metadata-Version: 2.4
Name: splinkclickhouse
Version: 0.4.1
Summary: Clickhouse backend support for Splink
Project-URL: Homepage, https://github.com/ADBond/splinkclickhouse
Project-URL: Documentation, https://adbond.github.io/splinkclickhouse/
Project-URL: Repository, https://github.com/ADBond/splinkclickhouse.git
Project-URL: Issues, https://github.com/ADBond/splinkclickhouse/issues
Project-URL: Changelog, https://github.com/ADBond/splinkclickhouse/blob/main/CHANGELOG.md
Author: Andrew Bond
License: MIT License
License-File: LICENSE
Keywords: data linking,deduplication,entity resolution,fuzzy matching,record linkage
Classifier: Development Status :: 3 - Alpha
Classifier: Intended Audience :: Developers
Classifier: Intended Audience :: Science/Research
Classifier: License :: OSI Approved :: MIT License
Classifier: Programming Language :: Python :: 3
Classifier: Programming Language :: Python :: 3.9
Classifier: Programming Language :: Python :: 3.10
Classifier: Programming Language :: Python :: 3.11
Classifier: Programming Language :: Python :: 3.12
Classifier: Programming Language :: Python :: 3.13
Classifier: Topic :: Scientific/Engineering
Classifier: Topic :: Scientific/Engineering :: Information Analysis
Requires-Python: >=3.9
Requires-Dist: clickhouse-connect>=0.7.0
Requires-Dist: splink>=4.0.6; python_version < '3.13'
Requires-Dist: splink>=4.0.7; python_version >= '3.13'
Provides-Extra: chdb
Requires-Dist: chdb<3,>=2.0.1; (python_version < '3.13') and extra == 'chdb'
